{
    "task1": {
        "input": {},
        "name": "Chart Classification",
        "output": {
            "chart_type": "Scatter"
        }
    },
    "task2": {
        "input": {
            "task1_output": {
                "chart_type": "Scatter"
            }
        },
        "name": "Text Detection and Recognition",
        "output": {
            "text_blocks": [
                {
                    "bb": {
                        "height": 19,
                        "width": 948,
                        "x0": 212,
                        "y0": 19
                    },
                    "text": "Export Growth and Share in World Export for India and Other Countries till 2014"
                },
                {
                    "bb": {
                        "height": 18,
                        "width": 40,
                        "x0": 666,
                        "y0": 924
                    },
                    "text": "2008"
                },
                {
                    "bb": {
                        "height": 40,
                        "width": 18,
                        "x0": 18,
                        "y0": 427
                    },
                    "text": "2009"
                },
                {
                    "bb": {
                        "height": 10,
                        "width": 18,
                        "x0": 189,
                        "y0": 863
                    },
                    "text": "0"
                },
                {
                    "bb": {
                        "height": 40,
                        "width": 18,
                        "x0": 336,
                        "y0": 863
                    },
                    "text": "2500"
                },
                {
                    "bb": {
                        "height": 40,
                        "width": 18,
                        "x0": 484,
                        "y0": 863
                    },
                    "text": "5000"
                },
                {
                    "bb": {
                        "height": 40,
                        "width": 18,
                        "x0": 631,
                        "y0": 863
                    },
                    "text": "7500"
                },
                {
                    "bb": {
                        "height": 50,
                        "width": 19,
                        "x0": 778,
                        "y0": 863
                    },
                    "text": "10000"
                },
                {
                    "bb": {
                        "height": 50,
                        "width": 19,
                        "x0": 926,
                        "y0": 863
                    },
                    "text": "12500"
                },
                {
                    "bb": {
                        "height": 50,
                        "width": 19,
                        "x0": 1073,
                        "y0": 863
                    },
                    "text": "15000"
                },
                {
                    "bb": {
                        "height": 50,
                        "width": 19,
                        "x0": 1221,
                        "y0": 863
                    },
                    "text": "17500"
                },
                {
                    "bb": {
                        "height": 18,
                        "width": 10,
                        "x0": 87,
                        "y0": 773
                    },
                    "text": "0"
                },
                {
                    "bb": {
                        "height": 18,
                        "width": 40,
                        "x0": 57,
                        "y0": 667
                    },
                    "text": "2000"
                },
                {
                    "bb": {
                        "height": 18,
                        "width": 40,
                        "x0": 57,
                        "y0": 562
                    },
                    "text": "4000"
                },
                {
                    "bb": {
                        "height": 18,
                        "width": 40,
                        "x0": 57,
                        "y0": 456
                    },
                    "text": "6000"
                },
                {
                    "bb": {
                        "height": 18,
                        "width": 40,
                        "x0": 57,
                        "y0": 350
                    },
                    "text": "8000"
                },
                {
                    "bb": {
                        "height": 18,
                        "width": 50,
                        "x0": 47,
                        "y0": 245
                    },
                    "text": "10000"
                },
                {
                    "bb": {
                        "height": 18,
                        "width": 50,
                        "x0": 47,
                        "y0": 139
                    },
                    "text": "12000"
                }
            ]
        }
    },
    "task3": {
        "input": {
            "task1_output": {
                "chart_type": "Scatter"
            },
            "task2_output": {
                "text_blocks": [
                    {
                        "bb": {
                            "height": 19,
                            "width": 948,
                            "x0": 212,
                            "y0": 19
                        },
                        "id": 0,
                        "text": "Export Growth and Share in World Export for India and Other Countries till 2014"
                    },
                    {
                        "bb": {
                            "height": 18,
                            "width": 40,
                            "x0": 666,
                            "y0": 924
                        },
                        "id": 1,
                        "text": "2008"
                    },
                    {
                        "bb": {
                            "height": 40,
                            "width": 18,
                            "x0": 18,
                            "y0": 427
                        },
                        "id": 2,
                        "text": "2009"
                    },
                    {
                        "bb": {
                            "height": 10,
                            "width": 18,
                            "x0": 189,
                            "y0": 863
                        },
                        "id": 3,
                        "text": "0"
                    },
                    {
                        "bb": {
                            "height": 40,
                            "width": 18,
                            "x0": 336,
                            "y0": 863
                        },
                        "id": 4,
                        "text": "2500"
                    },
                    {
                        "bb": {
                            "height": 40,
                            "width": 18,
                            "x0": 484,
                            "y0": 863
                        },
                        "id": 5,
                        "text": "5000"
                    },
                    {
                        "bb": {
                            "height": 40,
                            "width": 18,
                            "x0": 631,
                            "y0": 863
                        },
                        "id": 6,
                        "text": "7500"
                    },
                    {
                        "bb": {
                            "height": 50,
                            "width": 19,
                            "x0": 778,
                            "y0": 863
                        },
                        "id": 7,
                        "text": "10000"
                    },
                    {
                        "bb": {
                            "height": 50,
                            "width": 19,
                            "x0": 926,
                            "y0": 863
                        },
                        "id": 8,
                        "text": "12500"
                    },
                    {
                        "bb": {
                            "height": 50,
                            "width": 19,
                            "x0": 1073,
                            "y0": 863
                        },
                        "id": 9,
                        "text": "15000"
                    },
                    {
                        "bb": {
                            "height": 50,
                            "width": 19,
                            "x0": 1221,
                            "y0": 863
                        },
                        "id": 10,
                        "text": "17500"
                    },
                    {
                        "bb": {
                            "height": 18,
                            "width": 10,
                            "x0": 87,
                            "y0": 773
                        },
                        "id": 11,
                        "text": "0"
                    },
                    {
                        "bb": {
                            "height": 18,
                            "width": 40,
                            "x0": 57,
                            "y0": 667
                        },
                        "id": 12,
                        "text": "2000"
                    },
                    {
                        "bb": {
                            "height": 18,
                            "width": 40,
                            "x0": 57,
                            "y0": 562
                        },
                        "id": 13,
                        "text": "4000"
                    },
                    {
                        "bb": {
                            "height": 18,
                            "width": 40,
                            "x0": 57,
                            "y0": 456
                        },
                        "id": 14,
                        "text": "6000"
                    },
                    {
                        "bb": {
                            "height": 18,
                            "width": 40,
                            "x0": 57,
                            "y0": 350
                        },
                        "id": 15,
                        "text": "8000"
                    },
                    {
                        "bb": {
                            "height": 18,
                            "width": 50,
                            "x0": 47,
                            "y0": 245
                        },
                        "id": 16,
                        "text": "10000"
                    },
                    {
                        "bb": {
                            "height": 18,
                            "width": 50,
                            "x0": 47,
                            "y0": 139
                        },
                        "id": 17,
                        "text": "12000"
                    }
                ]
            }
        },
        "name": "Text Role Classification",
        "output": {
            "text_roles": [
                {
                    "id": 0,
                    "role": "chart_title"
                },
                {
                    "id": 1,
                    "role": "axis_title"
                },
                {
                    "id": 2,
                    "role": "axis_title"
                },
                {
                    "id": 3,
                    "role": "tick_label"
                },
                {
                    "id": 4,
                    "role": "tick_label"
                },
                {
                    "id": 5,
                    "role": "tick_label"
                },
                {
                    "id": 6,
                    "role": "tick_label"
                },
                {
                    "id": 7,
                    "role": "tick_label"
                },
                {
                    "id": 8,
                    "role": "tick_label"
                },
                {
                    "id": 9,
                    "role": "tick_label"
                },
                {
                    "id": 10,
                    "role": "tick_label"
                },
                {
                    "id": 11,
                    "role": "tick_label"
                },
                {
                    "id": 12,
                    "role": "tick_label"
                },
                {
                    "id": 13,
                    "role": "tick_label"
                },
                {
                    "id": 14,
                    "role": "tick_label"
                },
                {
                    "id": 15,
                    "role": "tick_label"
                },
                {
                    "id": 16,
                    "role": "tick_label"
                },
                {
                    "id": 17,
                    "role": "tick_label"
                }
            ]
        }
    },
    "task4": {
        "input": {
            "task1_output": {
                "chart_type": "Scatter"
            },
            "task2_output": {
                "text_blocks": [
                    {
                        "bb": {
                            "height": 19,
                            "width": 948,
                            "x0": 212,
                            "y0": 19
                        },
                        "id": 0,
                        "text": "Export Growth and Share in World Export for India and Other Countries till 2014"
                    },
                    {
                        "bb": {
                            "height": 18,
                            "width": 40,
                            "x0": 666,
                            "y0": 924
                        },
                        "id": 1,
                        "text": "2008"
                    },
                    {
                        "bb": {
                            "height": 40,
                            "width": 18,
                            "x0": 18,
                            "y0": 427
                        },
                        "id": 2,
                        "text": "2009"
                    },
                    {
                        "bb": {
                            "height": 10,
                            "width": 18,
                            "x0": 189,
                            "y0": 863
                        },
                        "id": 3,
                        "text": "0"
                    },
                    {
                        "bb": {
                            "height": 40,
                            "width": 18,
                            "x0": 336,
                            "y0": 863
                        },
                        "id": 4,
                        "text": "2500"
                    },
                    {
                        "bb": {
                            "height": 40,
                            "width": 18,
                            "x0": 484,
                            "y0": 863
                        },
                        "id": 5,
                        "text": "5000"
                    },
                    {
                        "bb": {
                            "height": 40,
                            "width": 18,
                            "x0": 631,
                            "y0": 863
                        },
                        "id": 6,
                        "text": "7500"
                    },
                    {
                        "bb": {
                            "height": 50,
                            "width": 19,
                            "x0": 778,
                            "y0": 863
                        },
                        "id": 7,
                        "text": "10000"
                    },
                    {
                        "bb": {
                            "height": 50,
                            "width": 19,
                            "x0": 926,
                            "y0": 863
                        },
                        "id": 8,
                        "text": "12500"
                    },
                    {
                        "bb": {
                            "height": 50,
                            "width": 19,
                            "x0": 1073,
                            "y0": 863
                        },
                        "id": 9,
                        "text": "15000"
                    },
                    {
                        "bb": {
                            "height": 50,
                            "width": 19,
                            "x0": 1221,
                            "y0": 863
                        },
                        "id": 10,
                        "text": "17500"
                    },
                    {
                        "bb": {
                            "height": 18,
                            "width": 10,
                            "x0": 87,
                            "y0": 773
                        },
                        "id": 11,
                        "text": "0"
                    },
                    {
                        "bb": {
                            "height": 18,
                            "width": 40,
                            "x0": 57,
                            "y0": 667
                        },
                        "id": 12,
                        "text": "2000"
                    },
                    {
                        "bb": {
                            "height": 18,
                            "width": 40,
                            "x0": 57,
                            "y0": 562
                        },
                        "id": 13,
                        "text": "4000"
                    },
                    {
                        "bb": {
                            "height": 18,
                            "width": 40,
                            "x0": 57,
                            "y0": 456
                        },
                        "id": 14,
                        "text": "6000"
                    },
                    {
                        "bb": {
                            "height": 18,
                            "width": 40,
                            "x0": 57,
                            "y0": 350
                        },
                        "id": 15,
                        "text": "8000"
                    },
                    {
                        "bb": {
                            "height": 18,
                            "width": 50,
                            "x0": 47,
                            "y0": 245
                        },
                        "id": 16,
                        "text": "10000"
                    },
                    {
                        "bb": {
                            "height": 18,
                            "width": 50,
                            "x0": 47,
                            "y0": 139
                        },
                        "id": 17,
                        "text": "12000"
                    }
                ]
            }
        },
        "name": "Axes Analysis",
        "output": {
            "_plot_bb": {
                "height": 800,
                "width": 1145,
                "x0": 113,
                "y0": 47
            },
            "axes": {
                "x-axis": [
                    {
                        "id": 3,
                        "tick_pt": {
                            "x": 206,
                            "y": 847
                        }
                    },
                    {
                        "id": 4,
                        "tick_pt": {
                            "x": 354,
                            "y": 847
                        }
                    },
                    {
                        "id": 5,
                        "tick_pt": {
                            "x": 501,
                            "y": 847
                        }
                    },
                    {
                        "id": 6,
                        "tick_pt": {
                            "x": 649,
                            "y": 847
                        }
                    },
                    {
                        "id": 7,
                        "tick_pt": {
                            "x": 796,
                            "y": 847
                        }
                    },
                    {
                        "id": 8,
                        "tick_pt": {
                            "x": 943,
                            "y": 847
                        }
                    },
                    {
                        "id": 9,
                        "tick_pt": {
                            "x": 1091,
                            "y": 847
                        }
                    },
                    {
                        "id": 10,
                        "tick_pt": {
                            "x": 1238,
                            "y": 847
                        }
                    }
                ],
                "y-axis": [
                    {
                        "id": 11,
                        "tick_pt": {
                            "x": 113,
                            "y": 779
                        }
                    },
                    {
                        "id": 12,
                        "tick_pt": {
                            "x": 113,
                            "y": 673
                        }
                    },
                    {
                        "id": 13,
                        "tick_pt": {
                            "x": 113,
                            "y": 568
                        }
                    },
                    {
                        "id": 14,
                        "tick_pt": {
                            "x": 113,
                            "y": 462
                        }
                    },
                    {
                        "id": 15,
                        "tick_pt": {
                            "x": 113,
                            "y": 356
                        }
                    },
                    {
                        "id": 16,
                        "tick_pt": {
                            "x": 113,
                            "y": 251
                        }
                    },
                    {
                        "id": 17,
                        "tick_pt": {
                            "x": 113,
                            "y": 145
                        }
                    }
                ]
            }
        }
    },
    "task5": {
        "input": {
            "task1_output": {
                "chart_type": "Scatter"
            },
            "task2_output": {
                "text_blocks": [
                    {
                        "bb": {
                            "height": 19,
                            "width": 948,
                            "x0": 212,
                            "y0": 19
                        },
                        "id": 0,
                        "text": "Export Growth and Share in World Export for India and Other Countries till 2014"
                    },
                    {
                        "bb": {
                            "height": 18,
                            "width": 40,
                            "x0": 666,
                            "y0": 924
                        },
                        "id": 1,
                        "text": "2008"
                    },
                    {
                        "bb": {
                            "height": 40,
                            "width": 18,
                            "x0": 18,
                            "y0": 427
                        },
                        "id": 2,
                        "text": "2009"
                    },
                    {
                        "bb": {
                            "height": 10,
                            "width": 18,
                            "x0": 189,
                            "y0": 863
                        },
                        "id": 3,
                        "text": "0"
                    },
                    {
                        "bb": {
                            "height": 40,
                            "width": 18,
                            "x0": 336,
                            "y0": 863
                        },
                        "id": 4,
                        "text": "2500"
                    },
                    {
                        "bb": {
                            "height": 40,
                            "width": 18,
                            "x0": 484,
                            "y0": 863
                        },
                        "id": 5,
                        "text": "5000"
                    },
                    {
                        "bb": {
                            "height": 40,
                            "width": 18,
                            "x0": 631,
                            "y0": 863
                        },
                        "id": 6,
                        "text": "7500"
                    },
                    {
                        "bb": {
                            "height": 50,
                            "width": 19,
                            "x0": 778,
                            "y0": 863
                        },
                        "id": 7,
                        "text": "10000"
                    },
                    {
                        "bb": {
                            "height": 50,
                            "width": 19,
                            "x0": 926,
                            "y0": 863
                        },
                        "id": 8,
                        "text": "12500"
                    },
                    {
                        "bb": {
                            "height": 50,
                            "width": 19,
                            "x0": 1073,
                            "y0": 863
                        },
                        "id": 9,
                        "text": "15000"
                    },
                    {
                        "bb": {
                            "height": 50,
                            "width": 19,
                            "x0": 1221,
                            "y0": 863
                        },
                        "id": 10,
                        "text": "17500"
                    },
                    {
                        "bb": {
                            "height": 18,
                            "width": 10,
                            "x0": 87,
                            "y0": 773
                        },
                        "id": 11,
                        "text": "0"
                    },
                    {
                        "bb": {
                            "height": 18,
                            "width": 40,
                            "x0": 57,
                            "y0": 667
                        },
                        "id": 12,
                        "text": "2000"
                    },
                    {
                        "bb": {
                            "height": 18,
                            "width": 40,
                            "x0": 57,
                            "y0": 562
                        },
                        "id": 13,
                        "text": "4000"
                    },
                    {
                        "bb": {
                            "height": 18,
                            "width": 40,
                            "x0": 57,
                            "y0": 456
                        },
                        "id": 14,
                        "text": "6000"
                    },
                    {
                        "bb": {
                            "height": 18,
                            "width": 40,
                            "x0": 57,
                            "y0": 350
                        },
                        "id": 15,
                        "text": "8000"
                    },
                    {
                        "bb": {
                            "height": 18,
                            "width": 50,
                            "x0": 47,
                            "y0": 245
                        },
                        "id": 16,
                        "text": "10000"
                    },
                    {
                        "bb": {
                            "height": 18,
                            "width": 50,
                            "x0": 47,
                            "y0": 139
                        },
                        "id": 17,
                        "text": "12000"
                    }
                ]
            }
        },
        "name": "Legend Analysis",
        "output": {
            "legend_pairs": []
        }
    },
    "task6": {
        "input": {
            "task1_output": {
                "chart_type": "Scatter"
            },
            "task2_output": {
                "text_blocks": [
                    {
                        "bb": {
                            "height": 19,
                            "width": 948,
                            "x0": 212,
                            "y0": 19
                        },
                        "id": 0,
                        "text": "Export Growth and Share in World Export for India and Other Countries till 2014"
                    },
                    {
                        "bb": {
                            "height": 18,
                            "width": 40,
                            "x0": 666,
                            "y0": 924
                        },
                        "id": 1,
                        "text": "2008"
                    },
                    {
                        "bb": {
                            "height": 40,
                            "width": 18,
                            "x0": 18,
                            "y0": 427
                        },
                        "id": 2,
                        "text": "2009"
                    },
                    {
                        "bb": {
                            "height": 10,
                            "width": 18,
                            "x0": 189,
                            "y0": 863
                        },
                        "id": 3,
                        "text": "0"
                    },
                    {
                        "bb": {
                            "height": 40,
                            "width": 18,
                            "x0": 336,
                            "y0": 863
                        },
                        "id": 4,
                        "text": "2500"
                    },
                    {
                        "bb": {
                            "height": 40,
                            "width": 18,
                            "x0": 484,
                            "y0": 863
                        },
                        "id": 5,
                        "text": "5000"
                    },
                    {
                        "bb": {
                            "height": 40,
                            "width": 18,
                            "x0": 631,
                            "y0": 863
                        },
                        "id": 6,
                        "text": "7500"
                    },
                    {
                        "bb": {
                            "height": 50,
                            "width": 19,
                            "x0": 778,
                            "y0": 863
                        },
                        "id": 7,
                        "text": "10000"
                    },
                    {
                        "bb": {
                            "height": 50,
                            "width": 19,
                            "x0": 926,
                            "y0": 863
                        },
                        "id": 8,
                        "text": "12500"
                    },
                    {
                        "bb": {
                            "height": 50,
                            "width": 19,
                            "x0": 1073,
                            "y0": 863
                        },
                        "id": 9,
                        "text": "15000"
                    },
                    {
                        "bb": {
                            "height": 50,
                            "width": 19,
                            "x0": 1221,
                            "y0": 863
                        },
                        "id": 10,
                        "text": "17500"
                    },
                    {
                        "bb": {
                            "height": 18,
                            "width": 10,
                            "x0": 87,
                            "y0": 773
                        },
                        "id": 11,
                        "text": "0"
                    },
                    {
                        "bb": {
                            "height": 18,
                            "width": 40,
                            "x0": 57,
                            "y0": 667
                        },
                        "id": 12,
                        "text": "2000"
                    },
                    {
                        "bb": {
                            "height": 18,
                            "width": 40,
                            "x0": 57,
                            "y0": 562
                        },
                        "id": 13,
                        "text": "4000"
                    },
                    {
                        "bb": {
                            "height": 18,
                            "width": 40,
                            "x0": 57,
                            "y0": 456
                        },
                        "id": 14,
                        "text": "6000"
                    },
                    {
                        "bb": {
                            "height": 18,
                            "width": 40,
                            "x0": 57,
                            "y0": 350
                        },
                        "id": 15,
                        "text": "8000"
                    },
                    {
                        "bb": {
                            "height": 18,
                            "width": 50,
                            "x0": 47,
                            "y0": 245
                        },
                        "id": 16,
                        "text": "10000"
                    },
                    {
                        "bb": {
                            "height": 18,
                            "width": 50,
                            "x0": 47,
                            "y0": 139
                        },
                        "id": 17,
                        "text": "12000"
                    }
                ]
            },
            "task3_output": {
                "text_roles": [
                    {
                        "id": 0,
                        "role": "chart_title"
                    },
                    {
                        "id": 1,
                        "role": "axis_title"
                    },
                    {
                        "id": 2,
                        "role": "axis_title"
                    },
                    {
                        "id": 3,
                        "role": "tick_label"
                    },
                    {
                        "id": 4,
                        "role": "tick_label"
                    },
                    {
                        "id": 5,
                        "role": "tick_label"
                    },
                    {
                        "id": 6,
                        "role": "tick_label"
                    },
                    {
                        "id": 7,
                        "role": "tick_label"
                    },
                    {
                        "id": 8,
                        "role": "tick_label"
                    },
                    {
                        "id": 9,
                        "role": "tick_label"
                    },
                    {
                        "id": 10,
                        "role": "tick_label"
                    },
                    {
                        "id": 11,
                        "role": "tick_label"
                    },
                    {
                        "id": 12,
                        "role": "tick_label"
                    },
                    {
                        "id": 13,
                        "role": "tick_label"
                    },
                    {
                        "id": 14,
                        "role": "tick_label"
                    },
                    {
                        "id": 15,
                        "role": "tick_label"
                    },
                    {
                        "id": 16,
                        "role": "tick_label"
                    },
                    {
                        "id": 17,
                        "role": "tick_label"
                    }
                ]
            },
            "task4_output": {
                "_plot_bb": {
                    "height": 800,
                    "width": 1145,
                    "x0": 113,
                    "y0": 47
                },
                "axes": {
                    "x-axis": [
                        {
                            "id": 3,
                            "tick_pt": {
                                "x": 206,
                                "y": 847
                            }
                        },
                        {
                            "id": 4,
                            "tick_pt": {
                                "x": 354,
                                "y": 847
                            }
                        },
                        {
                            "id": 5,
                            "tick_pt": {
                                "x": 501,
                                "y": 847
                            }
                        },
                        {
                            "id": 6,
                            "tick_pt": {
                                "x": 649,
                                "y": 847
                            }
                        },
                        {
                            "id": 7,
                            "tick_pt": {
                                "x": 796,
                                "y": 847
                            }
                        },
                        {
                            "id": 8,
                            "tick_pt": {
                                "x": 943,
                                "y": 847
                            }
                        },
                        {
                            "id": 9,
                            "tick_pt": {
                                "x": 1091,
                                "y": 847
                            }
                        },
                        {
                            "id": 10,
                            "tick_pt": {
                                "x": 1238,
                                "y": 847
                            }
                        }
                    ],
                    "y-axis": [
                        {
                            "id": 11,
                            "tick_pt": {
                                "x": 113,
                                "y": 779
                            }
                        },
                        {
                            "id": 12,
                            "tick_pt": {
                                "x": 113,
                                "y": 673
                            }
                        },
                        {
                            "id": 13,
                            "tick_pt": {
                                "x": 113,
                                "y": 568
                            }
                        },
                        {
                            "id": 14,
                            "tick_pt": {
                                "x": 113,
                                "y": 462
                            }
                        },
                        {
                            "id": 15,
                            "tick_pt": {
                                "x": 113,
                                "y": 356
                            }
                        },
                        {
                            "id": 16,
                            "tick_pt": {
                                "x": 113,
                                "y": 251
                            }
                        },
                        {
                            "id": 17,
                            "tick_pt": {
                                "x": 113,
                                "y": 145
                            }
                        }
                    ]
                }
            },
            "task5_output": {
                "legend_pairs": []
            }
        },
        "name": "Data Extraction",
        "output": {
            "data series": [
                {
                    "data": [
                        {
                            "x": "81.0",
                            "y": 62.0
                        },
                        {
                            "x": "1431.0",
                            "y": 1202.0
                        },
                        {
                            "x": "456.0",
                            "y": 316.0
                        },
                        {
                            "x": "291.0",
                            "y": 230.0
                        },
                        {
                            "x": "16160.0",
                            "y": 12554.0
                        },
                        {
                            "x": "1925.0",
                            "y": 1526.0
                        },
                        {
                            "x": "70.0",
                            "y": 56.0
                        },
                        {
                            "x": "132.0",
                            "y": 102.0
                        },
                        {
                            "x": "1446.0",
                            "y": 1120.0
                        },
                        {
                            "x": "472.0",
                            "y": 355.0
                        },
                        {
                            "x": "616.0",
                            "y": 485.0
                        },
                        {
                            "x": "422.0",
                            "y": 364.0
                        },
                        {
                            "x": "781.0",
                            "y": 581.0
                        },
                        {
                            "x": "198.0",
                            "y": 153.0
                        },
                        {
                            "x": "1287.0",
                            "y": 1056.0
                        },
                        {
                            "x": "313.0",
                            "y": 192.0
                        },
                        {
                            "x": "140.0",
                            "y": 120.0
                        },
                        {
                            "x": "187.0",
                            "y": 154.0
                        },
                        {
                            "x": "543.0",
                            "y": 407.0
                        }
                    ],
                    "name": ""
                }
            ],
            "visual elements": {
                "bars": [],
                "boxplots": [],
                "lines": [],
                "scatter points": [
                    {
                        "x": 212,
                        "y": 777
                    },
                    {
                        "x": 292,
                        "y": 717
                    },
                    {
                        "x": 234,
                        "y": 763
                    },
                    {
                        "x": 224,
                        "y": 768
                    },
                    {
                        "x": 1160,
                        "y": 117
                    },
                    {
                        "x": 321,
                        "y": 700
                    },
                    {
                        "x": 211,
                        "y": 777
                    },
                    {
                        "x": 215,
                        "y": 775
                    },
                    {
                        "x": 293,
                        "y": 721
                    },
                    {
                        "x": 235,
                        "y": 761
                    },
                    {
                        "x": 244,
                        "y": 755
                    },
                    {
                        "x": 232,
                        "y": 761
                    },
                    {
                        "x": 253,
                        "y": 749
                    },
                    {
                        "x": 219,
                        "y": 772
                    },
                    {
                        "x": 283,
                        "y": 724
                    },
                    {
                        "x": 226,
                        "y": 770
                    },
                    {
                        "x": 216,
                        "y": 774
                    },
                    {
                        "x": 218,
                        "y": 772
                    },
                    {
                        "x": 239,
                        "y": 759
                    }
                ]
            }
        }
    }
}